schrodinger2d/__init__.py
schrodinger2d/freeglut.dll
schrodinger2d/glew32.dll
schrodinger2d/main.py
schrodinger2d/pthreadVC2.dll
schrodinger2d/pyschrodinger2d.cp35-win_amd64.pyd
schrodinger2d-0.2.dist-info/DESCRIPTION.rst
schrodinger2d-0.2.dist-info/METADATA
schrodinger2d-0.2.dist-info/RECORD
schrodinger2d-0.2.dist-info/WHEEL
schrodinger2d-0.2.dist-info/metadata.json
schrodinger2d-0.2.dist-info/top_level.txt
