Metadata-Version: 2.0
Name: schrodinger2d
Version: 0.2
Summary: Equation de Schrodinger
Home-page: http://www.f-legrand.fr
Author: Frederic Legrand
Author-email: fredlegr@club-internet.fr
License: UNKNOWN
Platform: UNKNOWN
